setup.cfg
setup.py
python/gbdt/__init__.py
python/gbdt/_data_store.py
python/gbdt/_forest.py
python/gbdt/_forest_visualizer.py
python/gbdt/_gbdt.py
python/gbdt/_partial_dependency_plot.py
python/gbdt/_version.py
python/gbdt.egg-info/PKG-INFO
python/gbdt.egg-info/SOURCES.txt
python/gbdt.egg-info/dependency_links.txt
python/gbdt.egg-info/top_level.txt
python/gbdt/../../README.md
python/gbdt/lib/darwin_x86_64/libgbdt.so
python/gbdt/lib/linux_x86_64/libgbdt.so