Metadata-Version: 1.1
Name: gbdt
Version: 0.3.1.2
Summary: High performance implementation of GBDT family of algorithm
Home-page: https://github.com/yarny/gbdt
Author: Jiang Chen
Author-email: criver@gmail.com
License: Apache 2.0
Keywords: gbdt,machine learning,decision trees,forest
Platform: UNKNOWN
Classifier: Development Status :: 5 - Production/Stable
Classifier: Intended Audience :: Developers
Classifier: Operating System :: MacOS :: MacOS X
Classifier: Operating System :: POSIX :: Linux
Classifier: Topic :: Scientific/Engineering :: Artificial Intelligence
Classifier: License :: OSI Approved :: Apache Software License
Classifier: Programming Language :: C++
Classifier: Programming Language :: Python :: 2
Classifier: Programming Language :: Python :: 2.6
Classifier: Programming Language :: Python :: 2.7
